{
  "itemIdentifier": "ogc.bbr.wf4ever.wfdesc.Output",
  "name": "wfdesc:Output",
  "abstract": "An output parameter from a workflow process. Outputs produce data that can be consumed by inputs of other processes or as final workflow results.",
  "status": "under-development",
  "dateTimeAddition": "2025-11-07T00:00:00Z",
  "itemClass": "datatype",
  "register": "ogc-wf4ever",
  "version": "1.0",
  "dateOfLastChange": "2025-11-07",
  "profileOf": [
    "ogc.bbr.wf4ever.wfdesc.Parameter"
  ],
  "sources": [
    {
      "title": "Workflow Description Ontology - Output",
      "link": "http://purl.org/wf4ever/wfdesc#Output"
    }
  ],
  "maturity": "development",
  "scope": "unstable",
  "tags": [
    "workflow",
    "wfdesc",
    "output",
    "parameter"
  ],
  "group": "Wf4Ever - wfdesc"
}
